lyricspy/__init__.py
lyricspy/aio/__init__.py
LyricsPy-2.2.1.dist-info/METADATA
LyricsPy-2.2.1.dist-info/WHEEL
LyricsPy-2.2.1.dist-info/top_level.txt
LyricsPy-2.2.1.dist-info/RECORD
