Metadata-Version: 2.1
Name: LyricsPy
Version: 2.2.1
Summary: search lyrics on musixmatch.com
Home-page: https://github.com/amanoteam/LyricsPy
Author: Amano Team
Author-email: contact@amanoteam.com
Requires-Dist: httpx
